<?xml version="1.0" encoding="utf-8"?>
<MailSimSequence >
  <!-- LogFileLocation="\\puleung-7900\d$\" DisableOutlookPrompt="true" -->
    
  <OperationGroup Name="Single Run" OperationFile="Operations.xml">
    <Task Name="EventMonitor"/>
    <Task Name="MailSendToMyself" Sleep="10"/>
    <Task Name="MailSendTo2Recipients2Attachments" Sleep="10"/>
    <Task Name="MailSendTo5RandomRecipients5RandomAttachments" Sleep="10"/>
    <Task Name="MailSendTo1RandomRecipient" Sleep="10" Iterations = "2"/>
    <Task Name="MailReplyAllWithRandomAttachments" Sleep="10"/>
    <Task Name="MailForwardRandomlyWithRandomAttachments" Sleep="10"/>
    <Task Name="MailDelete2Items" Sleep="60"/>

  </OperationGroup>
  <!--
  <OperationGroup Name="Multiple Runs with 5 iterations" OperationFile="Operations.xml" Iterations="5" Sleep="120">
    <Task Name="MailSendToMyself" Sleep="10"/>
    <Task Name="MailSendTo2Recipients2Attachments" Sleep="10"/>
    <Task Name="MailSendTo5RandomRecipients5RandomAttachments" Sleep="10"/>
    <Task Name="MailSendTo1RandomRecipient" Sleep="10" Iterations = "2"/>
    <Task Name="MailReplyAllWithRandomAttachments" Sleep="10"/>
    <Task Name="MailDelete2Items" Sleep="60"/>

  </OperationGroup>

  
  <OperationGroup Name="Test2" OperationFile="C:\Users\puleung\Desktop\MailSim\MailSim\Operations.xml" Iterations="1" Sleep="10">
    <Task Name="FolderCreate"/>    
    <Task Name="MailSend3" Sleep="10"/>
    <Task Name="MailReply1"/>
    <Task Name="MailForward1"/>
    <Task Name="MailCopy1"/>
    <Task Name="FolderCreate"/>
    <Task Name="EventMonitor"/>
</OperationGroup>
-->
</MailSimSequence>
